wipp_client/__init__.py
wipp_client/wipp.py
wipp_client-0.2.0.dist-info/LICENSE
wipp_client-0.2.0.dist-info/METADATA
wipp_client-0.2.0.dist-info/WHEEL
wipp_client-0.2.0.dist-info/top_level.txt
wipp_client-0.2.0.dist-info/RECORD
